persianCalendar.py
persiancalendar-0.1.0.dist-info/METADATA
persiancalendar-0.1.0.dist-info/WHEEL
persiancalendar-0.1.0.dist-info/top_level.txt
persiancalendar-0.1.0.dist-info/RECORD
